setup.py
imageutils/__init__.py
imageutils/color.py
imageutils/compose.py
imageutils/size.py
imageutils.egg-info/PKG-INFO
imageutils.egg-info/SOURCES.txt
imageutils.egg-info/dependency_links.txt
imageutils.egg-info/requires.txt
imageutils.egg-info/top_level.txt